pocketmock/__init__.py
pocketmock-0.4.dist-info/DESCRIPTION.rst
pocketmock-0.4.dist-info/METADATA
pocketmock-0.4.dist-info/RECORD
pocketmock-0.4.dist-info/WHEEL
pocketmock-0.4.dist-info/metadata.json
pocketmock-0.4.dist-info/top_level.txt
