Metadata-Version: 2.0
Name: pocketmock
Version: 0.4
Summary: A very easy mocking library
Home-page: https://www.github.com/byxor/pocketmock
Author: Brandon Ibbotson
Author-email: brandon.ibbotson2@mail.dcu.ie
License: GPLv3
Platform: UNKNOWN
